<col:collection xmlns="http://cnx.rice.edu/collxml" xmlns:md="http://cnx.rice.edu/mdml" xmlns:col="http://cnx.rice.edu/collxml" xml:lang="en">  <metadata xmlns:md="http://cnx.rice.edu/mdml" mdml-version="0.5">  <md:content-id>col10839</md:content-id>  <md:title>Hướng dẫn soạn thảo bài giảng bằng công cụ eXe</md:title>      <md:license url="http://creativecommons.org/licenses/by/3.0/">Creative Commons Attribution License 3.0</md:license>  <md:language>vi</md:language>      <md:uuid>7322ce5b-5229-4cd6-889b-e27aff5bdb95</md:uuid>
<md:slug>huong-dan-soan-thao-bai-giang-bang-cong-cu-exe</md:slug>
</metadata>  <col:content>                        <col:subcollection>        <md:title>Giới thiệu và bước đầu làm việc với eXe</md:title>                                <col:content>                    <col:module document="m28561"/>                            <col:module document="m28604"/>                          </col:content>      </col:subcollection>                            <col:subcollection>        <md:title>Sử dụng eXe xây dựng nội dung cho bài giảng điện tử</md:title>                                <col:content>                    <col:module document="m28621"/>                            <col:module document="m28755"/>                            <col:module document="m30912"/>                          </col:content>      </col:subcollection>              <col:module document="m28756"/>                            <col:module document="m28531"/>                            <col:module document="m28655"/>                            <col:module document="m29020"/>                    </col:content></col:collection>